LICENSE
README.md
setup.py
libgutenberg/CommonOptions.py
libgutenberg/Cover.py
libgutenberg/DBUtils.py
libgutenberg/DublinCore.py
libgutenberg/DublinCoreMapping.py
libgutenberg/DummyConnectionPool.py
libgutenberg/GutenbergDatabase.py
libgutenberg/GutenbergDatabaseDublinCore.py
libgutenberg/GutenbergFiles.py
libgutenberg/GutenbergGlobals.py
libgutenberg/Logger.py
libgutenberg/MediaTypes.py
libgutenberg/Models.py
libgutenberg/__init__.py
libgutenberg.egg-info/PKG-INFO
libgutenberg.egg-info/SOURCES.txt
libgutenberg.egg-info/dependency_links.txt
libgutenberg.egg-info/requires.txt
libgutenberg.egg-info/top_level.txt